crossref_example_matching_strategy/__init__.py
crossref_example_matching_strategy/strategy.py
crossref_example_matching_strategy-0.2.1.dist-info/METADATA
crossref_example_matching_strategy-0.2.1.dist-info/WHEEL
crossref_example_matching_strategy-0.2.1.dist-info/entry_points.txt
crossref_example_matching_strategy-0.2.1.dist-info/licenses/LICENSE.txt
crossref_example_matching_strategy-0.2.1.dist-info/RECORD
