Metadata-Version: 2.4
Name: crossref-example-matching-strategy
Version: 0.2.1
Summary: This is meant to demonstrate how to create a strategy for use with the Crossref matching service (marple).
License-Expression: MIT
License-File: LICENSE.txt
Author: Jason Portenoy
Author-email: jportenoy@crossref.org
Requires-Python: >=3.11,<4.0
Classifier: Programming Language :: Python :: 3
Classifier: Programming Language :: Python :: 3.11
Classifier: Programming Language :: Python :: 3.12
Classifier: Programming Language :: Python :: 3.13
Classifier: Programming Language :: Python :: 3.14
Project-URL: Homepage, https://gitlab.com/crossref/example-matching-strategy
